LICENSE.txt
MANIFEST.in
README.md
requirements.txt
setup.py
aertb/__init__.py
aertb.egg-info/PKG-INFO
aertb.egg-info/SOURCES.txt
aertb.egg-info/dependency_links.txt
aertb.egg-info/entry_points.txt
aertb.egg-info/requires.txt
aertb.egg-info/top_level.txt
aertb/core/__init__.py
aertb/core/file_loader.py
aertb/core/hdf5tools.py
aertb/core/types.py
aertb/core/viz.py
aertb/core/loaders/__init__.py
aertb/core/loaders/aedat_loader.py
aertb/core/loaders/bin_loader.py
aertb/core/loaders/dat_loader.py
aertb/core/loaders/interface.py
aertb/core/loaders/mat_loader.py
cli/__init__.py
cli/click_gui.py
cli/shell.py
cli/test.py