Metadata-Version: 2.1
Name: aertb
Version: 0.3.4
Summary: UNKNOWN
Home-page: https://github.com/rfma23
Author: Rafael Mosca
Author-email: rafael.mosca@mail.polimi.it
License: UNKNOWN
Keywords: aedat,aer,dat,event,camera
Platform: UNKNOWN
Classifier:     Development Status :: 4 - Beta
Classifier:     Intended Audience :: Science/Research
Classifier:     Natural Language :: English
Classifier:     Programming Language :: Python :: 3
Classifier:     Programming Language :: Python :: 3.7
Classifier:     Topic :: Utilities
Classifier:     Topic :: Scientific/Engineering
Classifier:     Topic :: Software Development :: Libraries :: Python Modules
Classifier:     License :: OSI Approved :: MIT License
Classifier:     Operating System :: OS Independent
